Lab01/src/OperacionImplementacion.v
module OperacionImplementacion(
    input clk,
    input andd,
    input orr,
    input reset,
    input [3:0] a,
    input [3:0] sw,
    output reg [2:0] led,   // LED RGB: led[2]=Rojo, led[1]=Verde, led[0]=Azul
    output reg [3:0] y      // 4 LEDs de resultado
    );

    // Estados: 00 = apagado/invalido, 01 = OR, 10 = AND
    localparam OFF_ST = 2'b00;
    localparam OR_ST  = 2'b01;
    localparam AND_ST = 2'b10;

    reg [1:0] state = OFF_ST;

    // ---- Logica secuencial: transicion de estados ----
    always @(posedge clk or posedge reset) begin
        if (reset) begin
            state <= OFF_ST;
        end
        else begin
            case ({andd, orr})
                2'b10:   state <= AND_ST;  // solo andd presionado
                2'b01:   state <= OR_ST;   // solo orr presionado
                default: state <= OFF_ST;  // 2'b11 (ambos) o 2'b00 (ninguno)
            endcase
        end
    end

    // ---- Logica combinacional: salidas segun el estado ----
    always @(*) begin
        case (state)
            AND_ST: begin
                y   = a & sw;
                led = 3'b001; // Azul
            end
            OR_ST: begin
                y   = a | sw;
                led = 3'b010; // Verde
            end
            default: begin // OFF_ST
                y   = 4'b0000;
                led = 3'b100; // Rojo
            end
        endcase
    end

endmodule

Lab01/tb_OperacionImplementacion.v
`timescale 1ns/1ps

module tb_OperacionImplementacion;

    // ---- Señales de estímulo / observación ----
    reg        clk;
    reg        andd;
    reg        orr;
    reg        reset;
    reg  [3:0] a;
    reg  [3:0] sw;
    wire [2:0] led;
    wire [3:0] y;

    integer errores = 0;

    // ---- Instancia del DUT (Device Under Test) ----
    OperacionImplementacion DUT (
        .clk    (clk),
        .andd   (andd),
        .orr    (orr),
        .reset  (reset),
        .a      (a),
        .sw     (sw),
        .led    (led),
        .y      (y)
    );

    // ---- Generación de reloj: periodo 8 ns (125 MHz, igual que el XDC) ----
    initial clk = 1'b0;
    always #4 clk = ~clk;

    // ---- Tarea de verificación automática ----
    task check_output;
        input [3:0] y_esp;
        input [2:0] led_esp;
        input [319:0] etiqueta;
        begin
            if (y !== y_esp || led !== led_esp) begin
                errores = errores + 1;
                $display("[FALLO] t=%0t %-0s | esperado y=%b led=%b | obtenido y=%b led=%b",
                          $time, etiqueta, y_esp, led_esp, y, led);
            end else begin
                $display("[OK]    t=%0t %-0s | y=%b led=%b", $time, etiqueta, y, led);
            end
        end
    endtask

    initial begin
        // ---- Dump para GTKWave ----
        $dumpfile("OperacionImplementacion.vcd");
        $dumpvars(0, tb_OperacionImplementacion);

        // Valores iniciales
        andd  = 0; orr = 0; reset = 1;
        a     = 4'b0000; sw = 4'b0000;

        // ---- Reset inicial ----
        @(negedge clk);
        @(negedge clk);
        check_output(4'b0000, 3'b100, "Reset activo (OFF)");

        reset = 0;
        a  = 4'b1100;
        sw = 4'b1010;

        // ---- Caso 1: ningun selector activo -> OFF ----
        andd = 0; orr = 0;
        @(negedge clk); @(negedge clk);
        check_output(4'b0000, 3'b100, "andd=0 orr=0 (OFF)");

        // ---- Caso 2: solo orr -> OR ----
        andd = 0; orr = 1;
        @(negedge clk); @(negedge clk);
        check_output(a | sw, 3'b010, "andd=0 orr=1 (OR)");

        // Cambiar operandos estando en modo OR
        a = 4'b0110; sw = 4'b0011;
        @(negedge clk);
        check_output(a | sw, 3'b010, "OR con nuevos operandos");

        // ---- Caso 3: solo andd -> AND ----
        andd = 1; orr = 0;
        @(negedge clk); @(negedge clk);
        check_output(a & sw, 3'b001, "andd=1 orr=0 (AND)");

        a = 4'b1111; sw = 4'b1010;
        @(negedge clk);
        check_output(a & sw, 3'b001, "AND con nuevos operandos");

        // ---- Caso 4: ambos activos a la vez -> por defecto OFF ----
        andd = 1; orr = 1;
        @(negedge clk); @(negedge clk);
        check_output(4'b0000, 3'b100, "andd=1 orr=1 (OFF por defecto)");

        // ---- Caso 5: volver a AND y luego reset asincrono en medio del clk ----
        andd = 1; orr = 0;
        @(negedge clk); @(negedge clk);
        check_output(a & sw, 3'b001, "Vuelta a AND antes del reset asincrono");

        #2 reset = 1;              // reset asincrono, no alineado a flanco de reloj
        #1 check_output(4'b0000, 3'b100, "Reset asincrono forzado (OFF inmediato)");
        #3 reset = 0;

        // Con andd=1/orr=0 aun sostenidos, el siguiente flanco de reloj
        // regresa al DUT a modo AND (el reset solo fuerza OFF mientras esta activo)
        @(negedge clk); @(negedge clk);
        check_output(a & sw, 3'b001, "Tras liberar reset, vuelve a AND (andd=1 sostenido)");

        // ---- Caso 6: barrido de todas las combinaciones de a y sw en modo AND ----
        andd = 1; orr = 0;
        a = 4'b0000;
        repeat (4) begin
            sw = 4'b0000;
            repeat (4) begin
                @(negedge clk);
                check_output(a & sw, 3'b001, "Barrido AND");
                sw = sw + 4'b0101;
            end
            a = a + 4'b0011;
        end

        // ---- Resumen ----
        @(negedge clk);
        if (errores == 0)
            $display("\n==== TESTBENCH COMPLETO: TODOS LOS CASOS PASARON ====");
        else
            $display("\n==== TESTBENCH COMPLETO: %0d FALLO(S) DETECTADO(S) ====", errores);

        $finish;
    end

endmodule

Lab01/OperacionImplementacion.vcd
$date
	Fri Sep 25 13:27:36 2026
$end
$version
	Icarus Verilog
$end
$timescale
	1ps
$end
$scope module tb_OperacionImplementacion $end
$var wire 4 ! y [3:0] $end
$var wire 3 " led [2:0] $end
$var reg 4 # a [3:0] $end
$var reg 1 $ andd $end
$var reg 1 % clk $end
$var reg 1 & orr $end
$var reg 1 ' reset $end
$var reg 4 ( sw [3:0] $end
$var integer 32 ) errores [31:0] $end
$scope module DUT $end
$var wire 4 * a [3:0] $end
$var wire 1 $ andd $end
$var wire 1 % clk $end
$var wire 1 & orr $end
$var wire 1 ' reset $end
$var wire 4 + sw [3:0] $end
$var reg 3 , led [2:0] $end
$var reg 2 - state [1:0] $end
$var reg 4 . y [3:0] $end
$upscope $end
$scope task check_output $end
$var reg 320 / etiqueta [319:0] $end
$var reg 3 0 led_esp [2:0] $end
$var reg 4 1 y_esp [3:0] $end
$upscope $end
$upscope $end
$enddefinitions $end
#0
$dumpvars
bx 1
bx 0
bx /
b0 .
b0 -
b100 ,
b0 +
b0 *
b0 )
b0 (
1'
0&
0%
0$
b0 #
b100 "
b0 !
$end
#4000
1%
#8000
0%
#12000
1%
#16000
b1010 (
b1010 +
b1100 #
b1100 *
0'
b10100100110010101110011011001010111010000100000011000010110001101110100011010010111011001101111001000000010100001001111010001100100011000101001 /
b100 0
b0 1
0%
#20000
1%
#24000
0%
#28000
1%
#32000
1&
b11000010110111001100100011001000011110100110000001000000110111101110010011100100011110100110000001000000010100001001111010001100100011000101001 /
0%
#36000
b10 "
b10 ,
b1110 !
b1110 .
b1 -
1%
#40000
0%
#44000
1%
#48000
b111 !
b111 .
b11 (
b11 +
b110 #
b110 *
b110000101101110011001000110010000111101001100000010000001101111011100100111001000111101001100010010000000101000010011110101001000101001 /
b10 0
b1110 1
0%
#52000
1%
#56000
0&
1$
b100111101010010001000000110001101101111011011100010000001101110011101010110010101110110011011110111001100100000011011110111000001100101011100100110000101101110011001000110111101110011 /
b111 1
0%
#60000
b1 "
b1 ,
b10 !
b10 .
b10 -
1%
#64000
0%
#68000
1%
#72000
b1010 !
b1010 .
b1010 (
b1010 +
b1111 #
b1111 *
b11000010110111001100100011001000011110100110001001000000110111101110010011100100011110100110000001000000010100001000001010011100100010000101001 /
b1 0
b10 1
0%
#76000
1%
#80000
1&
b10000010100111001000100001000000110001101101111011011100010000001101110011101010110010101110110011011110111001100100000011011110111000001100101011100100110000101101110011001000110111101110011 /
b1010 1
0%
#84000
b100 "
b100 ,
b0 !
b0 .
b0 -
1%
#88000
0%
#92000
1%
#96000
0&
b11000010110111001100100011001000011110100110001001000000110111101110010011100100011110100110001001000000010100001001111010001100100011000100000011100000110111101110010001000000110010001100101011001100110010101100011011101000110111100101001 /
b100 0
b0 1
0%
#100000
b1 "
b1 ,
b1010 !
b1010 .
b10 -
1%
#104000
0%
#108000
1%
#112000
b101011001110101011001010110110001110100011000010010000001100001001000000100000101001110010001000010000001100001011011100111010001100101011100110010000001100100011001010110110000100000011100100110010101110011011001010111010000100000011000010111001101101001011011100110001101110010011011110110111001101111 /
b1 0
b1010 1
0%
#114000
b100 "
b100 ,
b0 !
b0 .
b0 -
1'
#115000
b10100100110010101110011011001010111010000100000011000010111001101101001011011100110001101110010011011110110111001101111001000000110011001101111011100100111101001100001011001000110111100100000001010000100111101000110010001100010000001101001011011100110110101100101011001000110100101100001011101000110111100101001 /
b100 0
b0 1
#116000
1%
#118000
0'
#120000
0%
#124000
b1 "
b1 ,
b1010 !
b1010 .
b10 -
1%
#128000
b0 !
b0 .
b0 (
b0 +
b0 #
b0 *
b1110010001000000111001001100101011100110110010101110100001011000010000001110110011101010110010101101100011101100110010100100000011000010010000001000001010011100100010000100000001010000110000101101110011001000110010000111101001100010010000001110011011011110111001101110100011001010110111001101001011001000110111100101001 /
b1 0
b1010 1
0%
#132000
1%
#136000
b101 (
b101 +
b100001001100001011100100111001001101001011001000110111100100000010000010100111001000100 /
b0 1
0%
#140000
1%
#144000
b1010 (
b1010 +
0%
#148000
1%
#152000
b1111 (
b1111 +
0%
#156000
1%
#160000
b11 #
b11 *
b0 (
b0 +
0%
#164000
1%
#168000
b1 !
b1 .
b101 (
b101 +
0%
#172000
1%
#176000
b10 !
b10 .
b1010 (
b1010 +
b1 1
0%
#180000
1%
#184000
b11 !
b11 .
b1111 (
b1111 +
b10 1
0%
#188000
1%
#192000
b0 !
b0 .
b110 #
b110 *
b0 (
b0 +
b11 1
0%
#196000
1%
#200000
b100 !
b100 .
b101 (
b101 +
b0 1
0%
#204000
1%
#208000
b10 !
b10 .
b1010 (
b1010 +
b100 1
0%
#212000
1%
#216000
b110 !
b110 .
b1111 (
b1111 +
b10 1
0%
#220000
1%
#224000
b0 !
b0 .
b1001 #
b1001 *
b0 (
b0 +
b110 1
0%
#228000
1%
#232000
b1 !
b1 .
b101 (
b101 +
b0 1
0%
#236000
1%
#240000
b1000 !
b1000 .
b1010 (
b1010 +
b1 1
0%
#244000
1%
#248000
b1001 !
b1001 .
b1111 (
b1111 +
b1000 1
0%
#252000
1%
#256000
b100 !
b100 .
b1100 #
b1100 *
b100 (
b100 +
b1001 1
0%
